README.md
setup.py
is_odd/__init__.py
is_odd/valid.py
is_odd.egg-info/PKG-INFO
is_odd.egg-info/SOURCES.txt
is_odd.egg-info/dependency_links.txt
is_odd.egg-info/top_level.txt