Metadata-Version: 2.1
Name: is-odd
Version: 0.1.1
Summary: A package to check if a number is odd or not
Home-page: https://github.com/datnguye/is-odd
Author: Dat Nguyen, Nam Vu
Author-email: datnguyen.it09@gmail.com, yvisvu@gmail.com
License: MIT
Platform: UNKNOWN
Requires-Python: >=3.7.5
